{
  "bg_img_url": "03-ela-ela-03-9780133245547-studio-images-ip3-ela-3-3-8_bk_japanesecanvas-ip3.jpg",
  "OriginalFileName": "ELA-9780133327236-AH.xml",
  "OriginalRelativeFileDirectory": null,
  "FlattenedJsonFileName": "ELA-9780133327236-AH.json",
  "MathMissionHeader": null,
  "header": {
    "lesson_id": "4336",
    "lesson_number": "8",
    "lesson_name": "Lesson 8",
    "lesson_types": null,
    "subject": 0,
    "subject_classificationSpecified": false,
    "grade": 3,
    "gradeSpecified": true,
    "unit": "5",
    "episode_number": null,
    "episode_name": null,
    "time_required": null,
    "version_number": null,
    "SubjectString": "ela"
  },
  "tasks": [
    {
      "task_id": 1,
      "description": "Author's Message",
      "routines": {
        "routine": {
          "routine_id": 1,
          "routine_name": "Opening"
        }
      },
      "steps": [
        {
          "step_id": 1,
          "description": null,
          "toc_description": "Think about the stories you have read in this unit so far. What elements did all of the stories have in common? ",
          "intended_end_user_roleSpecified": false,
          "interactivity_type": null,
          "layout": 0,
          "completedSpecified": false,
          "hints": null,
          "professional_development": null,
          "content_url": "grade3_ela_unit5_lesson8_task1_step1.html",
          "screenshot_url": "screenshot_grade3_ela_unit5_lesson8_task1_step1.png",
          "thumbnail_url": "thumbnail_grade3_ela_unit5_lesson8_task1_step1.png",
          "challenge_problem_step": false,
          "teacher_mode_content": "",
          "scrollable": false,
          "ResourceType": "Step",
          "LearningResourceId": "0063a7c1-299c-48fa-9095-7b1347c9e9c6",
          "NaturalKey": "L4336:T1:S1"
        }
      ],
      "ResourceType": "Task",
      "LearningResourceId": "423fb425-299c-4999-8ca1-b98007c4d0a6",
      "NaturalKey": "L4336:T1"
    },
    {
      "task_id": 2,
      "description": "What's Your Opinion?",
      "routines": {
        "routine": {
          "routine_id": 0,
          "routine_name": "Work Time"
        }
      },
      "steps": [
        {
          "step_id": 1,
          "description": null,
          "toc_description": "Strong readers usually have an opinion about what they are reading. ",
          "intended_end_user_roleSpecified": false,
          "interactivity_type": null,
          "layout": 3,
          "completedSpecified": false,
          "hints": null,
          "professional_development": null,
          "content_url": "grade3_ela_unit5_lesson8_task2_step1.html",
          "screenshot_url": "screenshot_grade3_ela_unit5_lesson8_task2_step1.png",
          "thumbnail_url": "thumbnail_grade3_ela_unit5_lesson8_task2_step1.png",
          "challenge_problem_step": false,
          "teacher_mode_content": "",
          "scrollable": false,
          "ResourceType": "Step",
          "LearningResourceId": "10c039e5-299c-4c48-8293-7acfa8eb0089",
          "NaturalKey": "L4336:T2:S1"
        }
      ],
      "ResourceType": "Task",
      "LearningResourceId": "174033e9-299c-44f0-bf36-541b2e0f6379",
      "NaturalKey": "L4336:T2"
    },
    {
      "task_id": 3,
      "description": "Write Your Opinion",
      "routines": {
        "routine": {
          "routine_id": 0,
          "routine_name": "Work Time"
        }
      },
      "steps": [
        {
          "step_id": 1,
          "description": null,
          "toc_description": "It is time to write a reading response to one of the books you have read so far in this unit. You can write about the one you liked the best or liked the least.",
          "intended_end_user_roleSpecified": false,
          "interactivity_type": null,
          "layout": 3,
          "completedSpecified": false,
          "hints": null,
          "professional_development": null,
          "content_url": "grade3_ela_unit5_lesson8_task3_step1.html",
          "screenshot_url": "screenshot_grade3_ela_unit5_lesson8_task3_step1.png",
          "thumbnail_url": "thumbnail_grade3_ela_unit5_lesson8_task3_step1.png",
          "challenge_problem_step": false,
          "teacher_mode_content": "",
          "scrollable": false,
          "ResourceType": "Step",
          "LearningResourceId": "71bd2b17-299c-4127-b0b3-5668e8940862",
          "NaturalKey": "L4336:T3:S1"
        }
      ],
      "ResourceType": "Task",
      "LearningResourceId": "c80a0386-299c-4220-8785-f85ef1d848eb",
      "NaturalKey": "L4336:T3"
    },
    {
      "task_id": 4,
      "description": "Independent Reading",
      "routines": {
        "routine": {
          "routine_id": 0,
          "routine_name": "Work Time"
        }
      },
      "steps": [
        {
          "step_id": 1,
          "description": null,
          "toc_description": "",
          "intended_end_user_roleSpecified": false,
          "interactivity_type": null,
          "layout": 0,
          "completedSpecified": false,
          "hints": null,
          "professional_development": null,
          "content_url": "grade3_ela_unit5_lesson8_task4_step1.html",
          "screenshot_url": "screenshot_grade3_ela_unit5_lesson8_task4_step1.png",
          "thumbnail_url": "thumbnail_grade3_ela_unit5_lesson8_task4_step1.png",
          "challenge_problem_step": false,
          "teacher_mode_content": "",
          "scrollable": false,
          "ResourceType": "Step",
          "LearningResourceId": "c99dbecd-299c-4bd9-b53b-246bb1b68536",
          "NaturalKey": "L4336:T4:S1"
        }
      ],
      "ResourceType": "Task",
      "LearningResourceId": "21c0405e-299c-4104-ac8f-fab4b4095f6a",
      "NaturalKey": "L4336:T4"
    },
    {
      "task_id": 5,
      "description": "Whole Group Share",
      "routines": {
        "routine": {
          "routine_id": 0,
          "routine_name": "Work Time"
        }
      },
      "steps": [
        {
          "step_id": 1,
          "description": null,
          "toc_description": "Did you find the author&#8217;s message in your book?",
          "intended_end_user_roleSpecified": false,
          "interactivity_type": null,
          "layout": 0,
          "completedSpecified": false,
          "hints": null,
          "professional_development": null,
          "content_url": "grade3_ela_unit5_lesson8_task5_step1.html",
          "screenshot_url": "screenshot_grade3_ela_unit5_lesson8_task5_step1.png",
          "thumbnail_url": "thumbnail_grade3_ela_unit5_lesson8_task5_step1.png",
          "challenge_problem_step": false,
          "teacher_mode_content": null,
          "scrollable": false,
          "ResourceType": "Step",
          "LearningResourceId": "9c9306bf-299c-4783-8d8d-553579d34e2e",
          "NaturalKey": "L4336:T5:S1"
        }
      ],
      "ResourceType": "Task",
      "LearningResourceId": "d62f9248-299c-48db-a874-c19301c2b985",
      "NaturalKey": "L4336:T5"
    },
    {
      "task_id": 6,
      "description": "What Your Story Says About You",
      "routines": {
        "routine": {
          "routine_id": 0,
          "routine_name": "Work Time"
        }
      },
      "steps": [
        {
          "step_id": 1,
          "description": null,
          "toc_description": "Stories are fun to read. They can also teach you about the experiences and culture of the storyteller. ",
          "intended_end_user_roleSpecified": false,
          "interactivity_type": null,
          "layout": 0,
          "completedSpecified": false,
          "hints": null,
          "professional_development": null,
          "content_url": "grade3_ela_unit5_lesson8_task6_step1.html",
          "screenshot_url": "screenshot_grade3_ela_unit5_lesson8_task6_step1.png",
          "thumbnail_url": "thumbnail_grade3_ela_unit5_lesson8_task6_step1.png",
          "challenge_problem_step": false,
          "teacher_mode_content": null,
          "scrollable": false,
          "ResourceType": "Step",
          "LearningResourceId": "3de837e2-299c-46c7-95c1-e2919f99d2cf",
          "NaturalKey": "L4336:T6:S1"
        }
      ],
      "ResourceType": "Task",
      "LearningResourceId": "51db26a2-299c-4b31-a908-ad225f60d762",
      "NaturalKey": "L4336:T6"
    },
    {
      "task_id": 7,
      "description": "Tell Your Story",
      "routines": {
        "routine": {
          "routine_id": 0,
          "routine_name": "Work TIme"
        }
      },
      "steps": [
        {
          "step_id": 1,
          "description": null,
          "toc_description": "Begin by thinking about the story you&nbsp;will tell. ",
          "intended_end_user_roleSpecified": false,
          "interactivity_type": null,
          "layout": 3,
          "completedSpecified": false,
          "hints": null,
          "professional_development": null,
          "content_url": "grade3_ela_unit5_lesson8_task7_step1.html",
          "screenshot_url": "screenshot_grade3_ela_unit5_lesson8_task7_step1.png",
          "thumbnail_url": "thumbnail_grade3_ela_unit5_lesson8_task7_step1.png",
          "challenge_problem_step": false,
          "teacher_mode_content": "",
          "scrollable": false,
          "ResourceType": "Step",
          "LearningResourceId": "9b2374b6-299c-44c3-ba09-90d4f96ca06b",
          "NaturalKey": "L4336:T7:S1"
        }
      ],
      "ResourceType": "Task",
      "LearningResourceId": "5b9e6d19-299c-494b-bcce-b50df3c555ed",
      "NaturalKey": "L4336:T7"
    },
    {
      "task_id": 8,
      "description": "Story Time",
      "routines": {
        "routine": {
          "routine_id": 0,
          "routine_name": "CLosing"
        }
      },
      "steps": [
        {
          "step_id": 1,
          "description": null,
          "toc_description": "Listen as a classmate retells a story. ",
          "intended_end_user_roleSpecified": false,
          "interactivity_type": null,
          "layout": 0,
          "completedSpecified": false,
          "hints": null,
          "professional_development": null,
          "content_url": "grade3_ela_unit5_lesson8_task8_step1.html",
          "screenshot_url": "screenshot_grade3_ela_unit5_lesson8_task8_step1.png",
          "thumbnail_url": "thumbnail_grade3_ela_unit5_lesson8_task8_step1.png",
          "challenge_problem_step": false,
          "teacher_mode_content": "",
          "scrollable": false,
          "ResourceType": "Step",
          "LearningResourceId": "7bbc4b23-299c-4729-ba73-0d30ce41a23d",
          "NaturalKey": "L4336:T8:S1"
        }
      ],
      "ResourceType": "Task",
      "LearningResourceId": "2dd60fa3-299c-4c52-b751-39bf2b092c62",
      "NaturalKey": "L4336:T8"
    },
    {
      "task_id": 9,
      "description": "Read!",
      "routines": {
        "routine": {
          "routine_id": 0,
          "routine_name": "homework"
        }
      },
      "steps": [
        {
          "step_id": 1,
          "description": null,
          "toc_description": "",
          "intended_end_user_roleSpecified": false,
          "interactivity_type": null,
          "layout": 0,
          "completedSpecified": false,
          "hints": null,
          "professional_development": null,
          "content_url": "grade3_ela_unit5_lesson8_task9_step1.html",
          "screenshot_url": "screenshot_grade3_ela_unit5_lesson8_task9_step1.png",
          "thumbnail_url": "thumbnail_grade3_ela_unit5_lesson8_task9_step1.png",
          "challenge_problem_step": false,
          "teacher_mode_content": "",
          "scrollable": false,
          "ResourceType": "Step",
          "LearningResourceId": "74a215d6-299c-4095-a692-b5ad1eda6b3f",
          "NaturalKey": "L4336:T9:S1"
        }
      ],
      "ResourceType": "Task",
      "LearningResourceId": "dfe5c94a-299c-4bc1-b68c-d917369845d2",
      "NaturalKey": "L4336:T9"
    }
  ],
  "ResourceType": "Lesson",
  "LearningResourceId": "282c5166-40f2-4c12-867b-3e6e9309edce",
  "NaturalKey": "L4336"
}